CPFcluster/core.py
CPFcluster/plotting.py
CPFcluster/utils.py
CPFcluster-3.0.dist-info/METADATA
CPFcluster-3.0.dist-info/WHEEL
CPFcluster-3.0.dist-info/top_level.txt
CPFcluster-3.0.dist-info/RECORD
