Metadata-Version: 2.1
Name: CPFcluster
Version: 3.0
Summary: An Implementation of Component-wise Peak Finding Clustering Method
Download-URL: https://github.com/tobinjo96/CPFcluster
Author: Joshua Tobin, Mimi Zhang
Author-email: tobinjo@tcd.ie
License: MIT
Keywords: density-peak-clustering,clustering,machine-learning
Classifier: Development Status :: 4 - Beta
Classifier: Intended Audience :: Developers
Classifier: Intended Audience :: Science/Research
Classifier: Topic :: Scientific/Engineering
Classifier: Topic :: Scientific/Engineering :: Artificial Intelligence
Classifier: Topic :: Scientific/Engineering :: Information Analysis
Classifier: Programming Language :: Python :: 3
Classifier: License :: OSI Approved :: MIT License
Classifier: Operating System :: OS Independent
Requires-Dist: numpy
Requires-Dist: scipy
Requires-Dist: scikit-learn
Requires-Dist: matplotlib
Requires-Dist: umap-learn
